wyzesense/__init__.py
wyzesense/__main__.py
wyzesense/gateway.py
wyzesense-0.0.5.dist-info/LICENSE
wyzesense-0.0.5.dist-info/METADATA
wyzesense-0.0.5.dist-info/WHEEL
wyzesense-0.0.5.dist-info/top_level.txt
wyzesense-0.0.5.dist-info/RECORD
