Metadata-Version: 2.1
Name: wyzesense
Version: 0.0.5
Summary: WyzeSense gateway library
Home-page: https://github.com/HclX/WyzeSensePy
Author: Xuan Xing
Author-email: hclxing@gmail.com
License: UNKNOWN
Platform: UNKNOWN
Classifier: Programming Language :: Python :: 2.7
Classifier: Programming Language :: Python :: 3
Classifier: License :: OSI Approved :: MIT License
Classifier: Operating System :: OS Independent
